rnasamba/__init__.py
rnasamba/cli.py
rnasamba/core/__init__.py
rnasamba/core/inputs.py
rnasamba/core/kmer.cpython-39-darwin.so
rnasamba/core/miniigloo.py
rnasamba/core/model.py
rnasamba/core/orf.cpython-39-darwin.so
rnasamba/core/sequences.py
rnasamba-0.2.5.dist-info/LICENSE
rnasamba-0.2.5.dist-info/METADATA
rnasamba-0.2.5.dist-info/WHEEL
rnasamba-0.2.5.dist-info/entry_points.txt
rnasamba-0.2.5.dist-info/top_level.txt
rnasamba-0.2.5.dist-info/RECORD
