Metadata-Version: 2.1
Name: rnasamba
Version: 0.2.5
Summary: A tool for computing the coding potential of RNA transcript sequences using deep learning.
Home-page: https://github.com/apcamargo/RNAsamba/
Author: Antonio Camargo, Vsevolod Sourkov
Author-email: antoniop.camargo@gmail.com
License: GNU General Public License v3.0
Keywords: bioinformatics,coding potential,transcriptomics,machine learning,neural networks
Platform: UNKNOWN
Classifier: Development Status :: 3 - Alpha
Classifier: Intended Audience :: Science/Research
Classifier: Natural Language :: English
Classifier: Topic :: Software Development :: Libraries
Classifier: Topic :: Scientific/Engineering :: Bio-Informatics
Classifier: License :: OSI Approved :: GNU General Public License (GPL)
Classifier: Programming Language :: Python :: 3
Requires-Python: >=3.6
